wsproto/__init__.py
wsproto/connection.py
wsproto/events.py
wsproto/extensions.py
wsproto/frame_protocol.py
wsproto/handshake.py
wsproto/py.typed
wsproto/typing.py
wsproto/utilities.py
wsproto-0.15.0.dist-info/LICENSE
wsproto-0.15.0.dist-info/METADATA
wsproto-0.15.0.dist-info/WHEEL
wsproto-0.15.0.dist-info/top_level.txt
wsproto-0.15.0.dist-info/RECORD
