Metadata-Version: 1.2
Name: wsproto
Version: 0.15.0
Summary: WebSockets state-machine based protocol implementation
Home-page: https://github.com/python-hyper/wsproto/
Author: Benno Rice
Author-email: benno@jeamland.net
License: MIT
Platform: UNKNOWN
Classifier: Development Status :: 4 - Beta
Classifier: Intended Audience :: Developers
Classifier: License :: OSI Approved :: MIT License
Classifier: Programming Language :: Python
Classifier: Programming Language :: Python :: 3
Classifier: Programming Language :: Python :: 3.6
Classifier: Programming Language :: Python :: 3.7
Classifier: Programming Language :: Python :: Implementation :: CPython
Classifier: Programming Language :: Python :: Implementation :: PyPy
Requires-Python: >=3.6.1
